README.md
setup.py
deep_data_package/__init__.py
deep_data_package/band_ratios.py
deep_data_package/example.py
deep_data_package/file_reader.py
deep_data_package/functions.py
deep_data_package/mapper.py
deep_data_package.egg-info/PKG-INFO
deep_data_package.egg-info/SOURCES.txt
deep_data_package.egg-info/dependency_links.txt
deep_data_package.egg-info/top_level.txt