Metadata-Version: 2.1
Name: deep-data-package
Version: 1.0.0
Summary: Hyperion and AVIRIS: file reader, multiple band indici calculator, and interactive mapper
Home-page: https://github.com/seansmith-mines/Deep-Data/archive/v1.0.0.tar.gz
Author: Team Deep-Data
Author-email: seansmith@mines.edu
License: UNKNOWN
Keywords: deep-data,AVIRIS,Hyperion,spectral
Platform: UNKNOWN
Classifier: Programming Language :: Python :: 3
Classifier: License :: OSI Approved :: MIT License
Classifier: Operating System :: OS Independent
